README.md
setup.py
mailscanner/__init__.py
mailscanner/parser.py
mailscanner/reader.py
mailscanner.egg-info/PKG-INFO
mailscanner.egg-info/SOURCES.txt
mailscanner.egg-info/dependency_links.txt
mailscanner.egg-info/top_level.txt
test/test_parser.py