Metadata-Version: 1.2
Name: mailscanner
Version: 1.0.1
Summary: Reads and parses email messages using IMAP
Home-page: http://github.com/coumbole/mailscanner
Author: Ville Kumpulainen
Author-email: ville.kumpulainen@gmail.com
License: GPL-3.0
Keywords: email,imap,parser
Platform: UNKNOWN
Classifier: Development Status :: 3 - Alpha
Classifier: Programming Language :: Python :: 3 :: Only
Classifier: License :: OSI Approved :: GNU General Public License v3 (GPLv3)
Requires-Python: >=3
